forge/__main__.py
forge/app.py
forge/commands/__init__.py
forge/commands/docs.py
forge/commands/lint.py
forge/commands/new.py
forge/commands/publish.py
forge/core/__init__.py
forge/core/utils.py
tf_forge-1.0.0.dist-info/METADATA
tf_forge-1.0.0.dist-info/WHEEL
tf_forge-1.0.0.dist-info/entry_points.txt
tf_forge-1.0.0.dist-info/top_level.txt
tf_forge-1.0.0.dist-info/RECORD
